eudex/__init__.py
eudex/core.py
eudex/test_eudex.py
eudex-0.0.1.dist-info/LICENSE
eudex-0.0.1.dist-info/WHEEL
eudex-0.0.1.dist-info/METADATA
eudex-0.0.1.dist-info/RECORD
