Metadata-Version: 2.1
Name: eudex
Version: 0.0.1
Summary: Python implementation of eudex, a fast phonetic reduction/hashing algorithm
Home-page: https://github.com/remiadon/eudex
License: UNKNOWN
Author: Rémi Adon
Author-email: remi.adon@gmail.com
Requires-Python: >=3
Classifier: Intended Audience :: Developers
Classifier: License :: OSI Approved :: BSD License
Classifier: Programming Language :: Python :: 3
Classifier: Topic :: Software Development :: Libraries :: Python Modules
Requires-Dist: sphinx ; extra == "doc"
Requires-Dist: pytest >=2.7.3 ; extra == "test"
Requires-Dist: pytest-cov ; extra == "test"
Provides-Extra: doc
Provides-Extra: test
